pymisp/__init__.py
pymisp/abstract.py
pymisp/api.py
pymisp/data/describeTypes.json
pymisp/data/misp-objects/objects/ADS/definition.json
pymisp/data/misp-objects/objects/abuseipdb/definition.json
pymisp/data/misp-objects/objects/ai-chat-prompt/definition.json
pymisp/data/misp-objects/objects/ail-leak/definition.json
pymisp/data/misp-objects/objects/ais/definition.json
pymisp/data/misp-objects/objects/ais-info/definition.json
pymisp/data/misp-objects/objects/android-app/definition.json
pymisp/data/misp-objects/objects/android-permission/definition.json
pymisp/data/misp-objects/objects/annotation/definition.json
pymisp/data/misp-objects/objects/anonymisation/definition.json
pymisp/data/misp-objects/objects/apivoid-email-verification/definition.json
pymisp/data/misp-objects/objects/artifact/definition.json
pymisp/data/misp-objects/objects/asn/definition.json
pymisp/data/misp-objects/objects/attack-pattern/definition.json
pymisp/data/misp-objects/objects/attack-step/definition.json
pymisp/data/misp-objects/objects/attacker-infra/definition.json
pymisp/data/misp-objects/objects/authentication-failure-report/definition.json
pymisp/data/misp-objects/objects/authenticode-signerinfo/definition.json
pymisp/data/misp-objects/objects/av-signature/definition.json
pymisp/data/misp-objects/objects/availability-impact/definition.json
pymisp/data/misp-objects/objects/bank-account/definition.json
pymisp/data/misp-objects/objects/bgp-hijack/definition.json
pymisp/data/misp-objects/objects/bgp-ranking/definition.json
pymisp/data/misp-objects/objects/blog/definition.json
pymisp/data/misp-objects/objects/boleto/definition.json
pymisp/data/misp-objects/objects/btc-transaction/definition.json
pymisp/data/misp-objects/objects/btc-wallet/definition.json
pymisp/data/misp-objects/objects/c2-list/definition.json
pymisp/data/misp-objects/objects/cap-alert/definition.json
pymisp/data/misp-objects/objects/cap-info/definition.json
pymisp/data/misp-objects/objects/cap-resource/definition.json
pymisp/data/misp-objects/objects/cert-pl-phishing/definition.json
pymisp/data/misp-objects/objects/cloth/definition.json
pymisp/data/misp-objects/objects/regripper-software-hive-windows-general-info/definition.json
pymisp-2.5.17.2.dist-info/METADATA
pymisp-2.5.17.2.dist-info/WHEEL
pymisp-2.5.17.2.dist-info/licenses/LICENSE
pymisp-2.5.17.2.dist-info/RECORD
